{
  "tubulares": [
    {
      "AssemblyName": "ESP",
      "Descripcion": "147X TUBING 3-1/2\" EUE",
      "Liner": "NO",
      "Profundidad": 5133.67,
      "ProfundidadTVD": 4852.6,
      "Colapso": 7400,
      "Yield": 6990,
      "TopeDeCemento": null,
      "TocTVD": null,
      "TopeDeCasing": 78.47,
      "cement_eval": "No efectivo"
    },
    {
      "AssemblyName": "7\" Intermediate Casing ",
      "Descripcion": "7\" Intermediate Casing ",
      "Liner": "NO",
      "Profundidad": 7061.42,
      "ProfundidadTVD": 6481.6,
      "Colapso": 10780,
      "Yield": 11640,
      "TopeDeCemento": 32.5,
      "TocTVD": 32.5,
      "TopeDeCasing": 2712.5,
      "cement_eval": "No efectivo"
    },
    {
      "AssemblyName": "7\" Intermediate Casing ",
      "Descripcion": "7\" Intermediate Casing ",
      "Liner": "NO",
      "Profundidad": 2712.5,
      "ProfundidadTVD": 6481.6,
      "Colapso": 6230,
      "Yield": 9950,
      "TopeDeCemento": 32.5,
      "TocTVD": 32.5,
      "TopeDeCasing": 32.5,
      "cement_eval": "No efectivo"
    },
    {
      "AssemblyName": "9 5/8\" Surface Casing ",
      "Descripcion": "9 5/8\" Surface Casing ",
      "Liner": "NO",
      "Profundidad": 1951.82,
      "ProfundidadTVD": 307.6,
      "Colapso": 2020,
      "Yield": 3520,
      "TopeDeCemento": 32.5,
      "TocTVD": 32.5,
      "TopeDeCasing": 32.5,
      "cement_eval": "No efectivo"
    },
    {
      "AssemblyName": "16\" Conductor Casing ",
      "Descripcion": "16\" Conductor Casing ",
      "Liner": "NO",
      "Profundidad": 42,
      "ProfundidadTVD": 42,
      "Colapso": 1020,
      "Yield": 2630,
      "TopeDeCemento": null,
      "TocTVD": null,
      "TopeDeCasing": 32.5,
      "cement_eval": "No efectivo"
    }
  ],
  "anulares": [
    {
      "index": 1,
      "Anular": "Anular C",
      "Densidad": 0,
      "Presion": 0
    },
    {
      "index": 2,
      "Anular": "Anular B",
      "Densidad": 0,
      "Presion": 0
    },
    {
      "index": 3,
      "Anular": "Anular A",
      "Densidad": 0,
      "Presion": 0
    },
    {
      "index": 4,
      "Anular": "Tubing",
      "Densidad": 0,
      "Presion": 0
    }
  ],
  "cabezales": [
    {
      "Anular": "Anular A",
      "RatingDePresion": 5000
    },
    {
      "Anular": "Anular B",
      "RatingDePresion": 5000
    },
    {
      "Anular": "Anular C",
      "RatingDePresion": 5000
    }
  ],
  "formaciones": [
    {
      "Formacion": "REAL",
      "MD Tope": 33,
      "TVD Tope": 33,
      "Gradiente Formacion": 0.48,
      "Gradiente Fractura": 1
    },
    {
      "Formacion": "Falla Principal T Norte",
      "MD Tope": 3170,
      "TVD Tope": 3114.27,
      "Gradiente Formacion": 0.48,
      "Gradiente Fractura": 1
    },
    {
      "Formacion": "COLORADO",
      "MD Tope": 3182,
      "TVD Tope": 3125.58,
      "Gradiente Formacion": 0.48,
      "Gradiente Fractura": 1
    },
    {
      "Formacion": "COLORADO BS",
      "MD Tope": 3370,
      "TVD Tope": 3302.32,
      "Gradiente Formacion": 0.494,
      "Gradiente Fractura": 1.05
    },
    {
      "Formacion": "COLORADO A0",
      "MD Tope": 3479,
      "TVD Tope": 3403.82,
      "Gradiente Formacion": 0.494,
      "Gradiente Fractura": 1.05
    },
    {
      "Formacion": "COLORADO A1",
      "MD Tope": 3540,
      "TVD Tope": 3460.48,
      "Gradiente Formacion": 0.494,
      "Gradiente Fractura": 1.05
    },
    {
      "Formacion": "COLORADO A1b",
      "MD Tope": 3754,
      "TVD Tope": 3658.37,
      "Gradiente Formacion": 0.494,
      "Gradiente Fractura": 1.05
    },
    {
      "Formacion": "COLORADO A2",
      "MD Tope": 4382,
      "TVD Tope": 4216.1,
      "Gradiente Formacion": 0.494,
      "Gradiente Fractura": 1.05
    },
    {
      "Formacion": "COLORADO A2i",
      "MD Tope": 4616,
      "TVD Tope": 4415.08,
      "Gradiente Formacion": 0.494,
      "Gradiente Fractura": 1.05
    },
    {
      "Formacion": "MUGROSA B0",
      "MD Tope": 4913,
      "TVD Tope": 4667.06,
      "Gradiente Formacion": 0.494,
      "Gradiente Fractura": 1.05
    },
    {
      "Formacion": "MUGROSA B1",
      "MD Tope": 5236,
      "TVD Tope": 4938.92,
      "Gradiente Formacion": 0.494,
      "Gradiente Fractura": 0.98
    },
    {
      "Formacion": "MUGROSA B2",
      "MD Tope": 5749,
      "TVD Tope": 5377.82,
      "Gradiente Formacion": 0.494,
      "Gradiente Fractura": 1.01
    },
    {
      "Formacion": "MUGROSA B2c",
      "MD Tope": 6086,
      "TVD Tope": 5666.64,
      "Gradiente Formacion": 0.494,
      "Gradiente Fractura": 1.01
    },
    {
      "Formacion": "MUGROSA B3",
      "MD Tope": 6496,
      "TVD Tope": 6014.94,
      "Gradiente Formacion": 0.52,
      "Gradiente Fractura": 0.98
    },
    {
      "Formacion": "MUGROSA B3i",
      "MD Tope": 6658,
      "TVD Tope": 6149.52,
      "Gradiente Formacion": 0.52,
      "Gradiente Fractura": 0.98
    },
    {
      "Formacion": "MUGROSA C",
      "MD Tope": 6913,
      "TVD Tope": 6360.67,
      "Gradiente Formacion": 0.52,
      "Gradiente Fractura": 0.98
    }
  ],
  "formaciones_exps": [],
  "accesorios": [
    {
      "Accesorio": "CHECK VALVE MODELO: SERIE 3-1/2. TIPO VALVE. CHECK POPPET TYPE 3-1/2 EUE API",
      "Profundidad": 4761.63,
      "Tipo": "SSSV",
      "Rating De Presion": 5000,
      "Assembly Al Que Pertenece": "ESP"
    },
    {
      "Accesorio": "SEAL UPPER  SERIE 400. TIPO: ESP 400 GUARDIAN XP / LSBPB HL HSS HT MT",
      "Profundidad": 4821.73,
      "Tipo": "Packer",
      "Rating De Presion": 5000,
      "Assembly Al Que Pertenece": "ESP"
    }
  ],
  "Liner_Hanger": [],
  "FITLOT": [
    {
      "Prueba": "LOT",
      "MD Prueba": 1962,
      "TVD Prueba": 1959.01,
      "EMW": 17.36
    },
    {
      "Prueba": "FIT",
      "MD Prueba": 1935,
      "TVD Prueba": 1932.37,
      "EMW": 16.77
    }
  ],
  "tubularesCols": [
    "AssemblyName",
    "Descripcion",
    "Liner",
    "Profundidad",
    "ProfundidadTVD",
    "Yield",
    "Colapso",
    "TopeDeCemento",
    "TocTVD",
    "TopeDeCasing",
    "cement_eval"
  ],
  "anularesCols": [ "Anular", "Densidad", "Presion" ],
  "cabezalesCols": [ "Anular", "Rating De Presion" ],
  "formacionesCols": [
    "Formacion",
    "MD Tope",
    "TVD Tope",
    "Gradiente Formacion",
    "Gradiente Fractura"
  ],
  "formacionesExpsCols": [ "Formacion", "TVD Tope", "Anular" ],
  "accesoriosCols": [
    "Accesorio",
    "Tipo",
    "Profundidad",
    "Rating De Presion",
    "Assembly Al Que Pertenece"
  ],
  "Liner_HangerCols": [
    "Liner Hanger",
    "Profundidad",
    "Rating De Presion",
    "Assembly Al Que Pertenece"
  ],
  "FIT&LOTCols": [ "Prueba", "MD Prueba", "TVD Prueba", "EMW" ],
  "SF": 0.9
}
