{
  "tubulares": [
    {
      "AssemblyName": "PROD STRING + INSTRUMENTS",
      "Descripcion": "TUBING, 3-1/2  EUE 9,3 lb/ft, N80, PIN-BOX",
      "Liner": "NO",
      "Profundidad": 6949.29,
      "ProfundidadTVD": 6152.79,
      "Colapso": 10530,
      "Yield": 10160,
      "TopeDeCemento": null,
      "TocTVD": null,
      "TopeDeCasing": 36.88,
      "cement_eval": "No efectivo",
      "SectType": "TBG"
    },
    {
      "AssemblyName": "PRODUCTION LINER",
      "Descripcion": "PRODUCTION LINER",
      "Liner": "SI",
      "Profundidad": 7808,
      "ProfundidadTVD": 6919.2,
      "Colapso": 7030,
      "Yield": 8160,
      "TopeDeCemento": 7065,
      "TocTVD": 6521,
      "TopeDeCasing": 7084.4,
      "cement_eval": "NA",
      "SectType": "CAS",
      "Diameter": 7
    },
    {
      "AssemblyName": "INTERMEDIATE CASING 1",
      "Descripcion": "INTERMEDIATE CASING 1",
      "Liner": "NO",
      "Profundidad": 7275,
      "ProfundidadTVD": 6436.4,
      "Colapso": 7930,
      "Yield": 10900,
      "TopeDeCemento": 2133,
      "TocTVD": 2114,
      "TopeDeCasing": 5821.7,
      "cement_eval": "NA",
      "SectType": "CAS",
      "Diameter": 9.625
    },
    {
      "AssemblyName": "INTERMEDIATE CASING 1",
      "Descripcion": "INTERMEDIATE CASING 1",
      "Liner": "NO",
      "Profundidad": 5821.7,
      "ProfundidadTVD": 6436.4,
      "Colapso": 5310,
      "Yield": 9440,
      "TopeDeCemento": 2133,
      "TocTVD": 2114,
      "TopeDeCasing": 32.5,
      "cement_eval": "NA",
      "SectType": "CAS",
      "Diameter": 9.625
    },
    {
      "AssemblyName": "SURFACE CASING",
      "Descripcion": "SURFACE CASING",
      "Liner": "NO",
      "Profundidad": 2333,
      "ProfundidadTVD": 2307.7,
      "Colapso": 1950,
      "Yield": 3450,
      "TopeDeCemento": 32.5,
      "TocTVD": 32.5,
      "TopeDeCasing": 1269.4,
      "cement_eval": "NA",
      "SectType": "CAS",
      "Diameter": 13.375
    },
    {
      "AssemblyName": "SURFACE CASING",
      "Descripcion": "SURFACE CASING",
      "Liner": "NO",
      "Profundidad": 1269.4,
      "ProfundidadTVD": 2307.7,
      "Colapso": 1130,
      "Yield": 2730,
      "TopeDeCemento": 32.5,
      "TocTVD": 32.5,
      "TopeDeCasing": 32.5,
      "cement_eval": "NA",
      "SectType": "CAS",
      "Diameter": 13.37500000005346
    },
    {
      "AssemblyName": "CONDUCTOR",
      "Descripcion": "CONDUCTOR",
      "Liner": "NO",
      "Profundidad": 55,
      "ProfundidadTVD": 55,
      "Colapso": 7501.32,
      "Yield": 8431.11,
      "TopeDeCemento": null,
      "TocTVD": null,
      "TopeDeCasing": 32.5,
      "cement_eval": "NA",
      "SectType": "CAS",
      "Diameter": 20
    }
  ],
  "anulares": [
    {
      "index": 1,
      "Anular": "Anular A",
      "Densidad": 8.7,
      "Presion": 0
    },
    {
      "index": 2,
      "Anular": "Anular B",
      "Densidad": 8.4,
      "Presion": 0
    },
    {
      "index": 3,
      "Anular": "Tubing",
      "Densidad": 8.7,
      "Presion": 0
    }
  ],
  "cabezales": [
    {
      "Anular": "Anular B",
      "RatingDePresion": 5000
    },
    {
      "Anular": "Anular A",
      "RatingDePresion": 3000
    }
  ],
  "formaciones": [
    {
      "Formacion": "GUAYABO",
      "MdTope": 32.47000000000003,
      "TvdTope": 32.47,
      "MdBase": 1099.97,
      "TvdBase": 1099.97,
      "GradienteFormacion": 0,
      "GradienteFractura": 0
    },
    {
      "Formacion": "CARBONERA SUPERIOR",
      "MdTope": 1099.97,
      "TvdTope": 1099.97,
      "MdBase": 1866.97,
      "TvdBase": 1866.97,
      "GradienteFormacion": 0,
      "GradienteFractura": 0
    },
    {
      "Formacion": "LUTITA E",
      "MdTope": 1866.9700000000003,
      "TvdTope": 1866.97,
      "MdBase": 2074.97,
      "TvdBase": 2074.97,
      "GradienteFormacion": 0,
      "GradienteFractura": 0
    },
    {
      "Formacion": "C1",
      "MdTope": 2074.9700000000003,
      "TvdTope": 2058.85,
      "MdBase": 3183.97,
      "TvdBase": 3119.62,
      "GradienteFormacion": 0,
      "GradienteFractura": 0
    },
    {
      "Formacion": "ARENISCAS DE CARBONERA",
      "MdTope": 3183.9700000000003,
      "TvdTope": 3119.62,
      "MdBase": 3607.97,
      "TvdBase": 3524.55,
      "GradienteFormacion": 0,
      "GradienteFractura": 0
    },
    {
      "Formacion": "C2",
      "MdTope": 3607.969999999999,
      "TvdTope": 3461.42,
      "MdBase": 6064.97,
      "TvdBase": 5417.13,
      "GradienteFormacion": 0,
      "GradienteFractura": 0
    },
    {
      "Formacion": "E3",
      "MdTope": 6064.969999999999,
      "TvdTope": 5417.13,
      "MdBase": 6482.97,
      "TvdBase": 5757.18,
      "GradienteFormacion": 0,
      "GradienteFractura": 0
    },
    {
      "Formacion": "T1",
      "MdTope": 6482.969999999999,
      "TvdTope": 5757.18,
      "MdBase": 6661.97,
      "TvdBase": 5906.1,
      "GradienteFormacion": 0,
      "GradienteFractura": 0
    },
    {
      "Formacion": "E4",
      "MdTope": 6661.969999999999,
      "TvdTope": 5906.39,
      "MdBase": 7279.97,
      "TvdBase": 6436.96,
      "GradienteFormacion": 0,
      "GradienteFractura": 0
    },
    {
      "Formacion": "T2",
      "MdTope": 7284.969999999999,
      "TvdTope": 6441.29,
      "MdBase": 7312.97,
      "TvdBase": 6465.48,
      "GradienteFormacion": 0,
      "GradienteFractura": 0
    },
    {
      "Formacion": "K1 SUPERIOR",
      "MdTope": 7312.969999999999,
      "TvdTope": 6465.48,
      "MdBase": 7494.97,
      "TvdBase": 6622.75,
      "GradienteFormacion": 0,
      "GradienteFractura": 0
    },
    {
      "Formacion": "K1 INFERIOR",
      "MdTope": 7494.969999999999,
      "TvdTope": 6622.75,
      "MdBase": 7691.97,
      "TvdBase": 6792.97,
      "GradienteFormacion": 0.334,
      "GradienteFractura": 0.494
    },
    {
      "Formacion": "K2",
      "MdTope": 7691.969999999999,
      "TvdTope": 6792.97,
      "MdBase": 1363.4,
      "TvdBase": 1363.4,
      "GradienteFormacion": 0,
      "GradienteFractura": 0
    }
  ],
  "formaciones_exps": [],
  "accesorios": [],
  "Liner_Hanger": [
    {
      "LinerHangerName": "PBR",
      "ProfundidadMd": 7065.369999999999,
      "RatingDePresion": 8000,
      "AssemblyAlQuePertenece": "PRODUCTION LINER",
      "BurstPressure": 8160
    },
    {
      "LinerHangerName": "LINER HANGER VERSAFLEX 7 IN",
      "ProfundidadMd": 7075.969999999999,
      "RatingDePresion": 8000,
      "AssemblyAlQuePertenece": "PRODUCTION LINER",
      "BurstPressure": 8160
    }
  ],
  "FITLOT": [
    {
      "well_id": "r2edFaIgZ1",
      "wellbore_id": "s2bHGqmJCc",
      "hole_sect_group_id": "qEpin",
      "wellbore_integ_id": "HKMjD",
      "date_test": "2022-12-12T00:00:00.000Z",
      "weight_lot_emw": 13.47052449067779,
      "is_absorption": null,
      "is_fracture": null,
      "lot_press": 356,
      "total_bh_press": 1614.3636363648002,
      "lot_md": 953.57,
      "lot_tvd": 943.57,
      "test_type": "FIT  ",
      "weight_lot_amw": 10.5,
      "pump_rate": 0.39,
      "open_hole_length": 10,
      "md_water": null,
      "lot_formation": "C1",
      "lot_lithology": null,
      "lot_azimuth": 223.945687167918,
      "lot_inclination": 16.00000000000068,
      "test_result": null,
      "is_test_continuous": null,
      "fluid_api_water_loss": null,
      "stabilization_pressure": null,
      "stabilization_time": null,
      "vol_fluid_returned": null,
      "vol_fluid_absorbed": null,
      "charge_loss": null,
      "pump_height": null,
      "injection_point": null,
      "remarks": null,
      "total_volume": null,
      "is_injection": null,
      "limit_required": null,
      "formation_strength": null,
      "hydrostatic_head": null,
      "mud_compressibilty": null,
      "gauge_height": null,
      "data_quality": null,
      "friction_pressure": null,
      "pwd_sensor_offset": null,
      "dh_mud_weight": null,
      "bh_max_pressure": null,
      "bh_max_emw": null,
      "data_source": null,
      "quality_flag": null,
      "hole_name": "HUECO INTERMEDIO 1"
    }
  ],
  "SecurityFactors": {
    "Collapse": 0.9803921568627451,
    "Burst": 0.9009009009009008
  },
  "Survey": [
    {
      "Md": -1363.43,
      "Inc": 0,
      "Azi": 0.0256871679176644,
      "Tvd": -1363.43,
      "Ns": 0,
      "Ew": 0
    },
    {
      "Md": -1330.93,
      "Inc": 0,
      "Azi": 0.0306871678860865,
      "Tvd": -1330.93,
      "Ns": 0,
      "Ew": 0
    },
    {
      "Md": -1007.4300000000001,
      "Inc": 0.71,
      "Azi": 240.875687167886,
      "Tvd": -1007.438279252593,
      "Ns": -0.975531390267197,
      "Ew": -1.75093513707296
    },
    {
      "Md": -917.4300000000001,
      "Inc": 0.88,
      "Azi": 238.625687167886,
      "Tvd": -917.4469735847861,
      "Ns": -1.6067455065907899,
      "Ew": -2.8281224663149804
    },
    {
      "Md": -827.4300000000001,
      "Inc": 1.25,
      "Azi": 243.515687167886,
      "Tvd": -827.462658914961,
      "Ns": -2.4043441609869802,
      "Ew": -4.29684796421385
    },
    {
      "Md": -737.4300000000001,
      "Inc": 1.0899999999999999,
      "Azi": 236.90568716788601,
      "Tvd": -737.481410716126,
      "Ns": -3.30953331153611,
      "Ew": -5.892660417002479
    },
    {
      "Md": -643.4300000000001,
      "Inc": 1.5999999999999999,
      "Azi": 228.105687167886,
      "Tvd": -643.5075216759841,
      "Ns": -4.674038348596719,
      "Ew": -7.618567847870139
    },
    {
      "Md": -548.4300000000001,
      "Inc": 2.1599999999999997,
      "Azi": 214.93568716788602,
      "Tvd": -548.55859737498,
      "Ns": -7.0273677029344395,
      "Ew": -9.63106274028129
    },
    {
      "Md": -453.43,
      "Inc": 2.8699999999999997,
      "Azi": 212.165687167886,
      "Tvd": -453.650676798168,
      "Ns": -10.50836094302818,
      "Ew": -11.92245829329457
    },
    {
      "Md": -360.43,
      "Inc": 3.69,
      "Azi": 215.565687167886,
      "Tvd": -360.803729418626,
      "Ns": -14.91370824587279,
      "Ew": -14.90263859803153
    },
    {
      "Md": -265.43,
      "Inc": 4.779999999999999,
      "Azi": 215.635687167886,
      "Tvd": -266.06455053562405,
      "Ns": -20.61756317870891,
      "Ew": -18.98697817547143
    },
    {
      "Md": -170.43,
      "Inc": 6.14,
      "Azi": 216.835687167886,
      "Tvd": -171.497767262172,
      "Ns": -27.901098620330888,
      "Ew": -24.3392619176312
    },
    {
      "Md": -75.43000000000005,
      "Inc": 7.51,
      "Azi": 219.015687167886,
      "Tvd": -77.1730489913284,
      "Ns": -36.7913872041028,
      "Ew": -31.293763158236228
    },
    {
      "Md": 18.56999999999993,
      "Inc": 8.020000000000001,
      "Azi": 220.315687167886,
      "Tvd": 15.964788988866529,
      "Ns": -46.56424856003943,
      "Ew": -39.40357604030035
    },
    {
      "Md": 113.57,
      "Inc": 9.020000000000001,
      "Azi": 223.15568716788601,
      "Tvd": 109.91561698242701,
      "Ns": -57.05027861728284,
      "Ew": -48.78523827027336
    },
    {
      "Md": 208.57000000000002,
      "Inc": 9.65,
      "Azi": 223.785687167886,
      "Tvd": 203.657066912261,
      "Ns": -68.23128251439867,
      "Ew": -59.38865275406718
    },
    {
      "Md": 303.57000000000005,
      "Inc": 10.58,
      "Azi": 222.805687167886,
      "Tvd": 297.179547783615,
      "Ns": -80.37842338499544,
      "Ew": -70.82489442308481
    },
    {
      "Md": 397.57000000000005,
      "Inc": 11.49,
      "Azi": 224.105687167886,
      "Tvd": 389.440704348688,
      "Ns": -93.4325561835847,
      "Ew": -83.20508024892365
    },
    {
      "Md": 492.57000000000005,
      "Inc": 12.639999999999999,
      "Azi": 224.455687167886,
      "Tvd": 482.340712319639,
      "Ns": -107.64646154076,
      "Ew": -97.07047647561728
    },
    {
      "Md": 587.57,
      "Inc": 12.81,
      "Azi": 224.795687167886,
      "Tvd": 575.00735140465,
      "Ns": -122.539249640337,
      "Ew": -111.770509042548
    },
    {
      "Md": 682.57,
      "Inc": 14.26,
      "Azi": 224.18568716788602,
      "Tvd": 667.3665121953281,
      "Ns": -138.40372350130602,
      "Ew": -127.34669482675001
    },
    {
      "Md": 777.57,
      "Inc": 15.4,
      "Azi": 224.135687167886,
      "Tvd": 759.200500728881,
      "Ns": -155.847332623725,
      "Ew": -144.286036074733
    },
    {
      "Md": 872.57,
      "Inc": 16.25,
      "Azi": 225.115687167886,
      "Tvd": 850.599242405049,
      "Ns": -174.280400026013,
      "Ew": -162.487963834119
    },
    {
      "Md": 1074.569999999999,
      "Inc": 18.649999999999988,
      "Azi": 226.46568716788602,
      "Tvd": 1043.289711164559,
      "Ns": -216.47790818747,
      "Ew": -205.93469837817003
    },
    {
      "Md": 1169.569999999999,
      "Inc": 19.12999999999999,
      "Azi": 224.43568716788602,
      "Tvd": 1133.173912095275,
      "Ns": -238.05581476935902,
      "Ew": -227.845258777429
    },
    {
      "Md": 1264.569999999999,
      "Inc": 19.77,
      "Azi": 223.755687167886,
      "Tvd": 1222.7521441375482,
      "Ns": -260.775891354885,
      "Ew": -249.85509484027602
    },
    {
      "Md": 1359.569999999999,
      "Inc": 21.349999999999998,
      "Azi": 224.035687167886,
      "Tvd": 1311.69831683819,
      "Ns": -284.814377810457,
      "Ew": -272.988521173261
    },
    {
      "Md": 1454.569999999999,
      "Inc": 22.369999999999997,
      "Azi": 223.725687167886,
      "Tvd": 1399.8663424833062,
      "Ns": -310.31124010423906,
      "Ew": -297.505206627925
    },
    {
      "Md": 1549.569999999999,
      "Inc": 23.759999999999998,
      "Azi": 223.71568716788602,
      "Tvd": 1487.269993208771,
      "Ns": -337.209212246609,
      "Ew": -323.22792615801404
    },
    {
      "Md": 1643.5699999999993,
      "Inc": 25.329999999999988,
      "Azi": 223.575687167886,
      "Tvd": 1572.7730428300101,
      "Ns": -365.46551982942003,
      "Ew": -350.17706280930406
    },
    {
      "Md": 1738.5699999999993,
      "Inc": 25.959999999999997,
      "Azi": 223.885687167886,
      "Tvd": 1658.41447497762,
      "Ns": -395.17427537578004,
      "Ew": -378.59958718398906
    },
    {
      "Md": 1831.5699999999993,
      "Inc": 27.009999999999998,
      "Azi": 224.385687167886,
      "Tvd": 1741.653171711428,
      "Ns": -424.937317578398,
      "Ew": -407.482587692278
    },
    {
      "Md": 1926.5699999999993,
      "Inc": 28.419999999999998,
      "Azi": 223.885687167886,
      "Tvd": 1825.751995429403,
      "Ns": -456.648512069178,
      "Ew": -438.24490478972905
    },
    {
      "Md": 2021.5699999999993,
      "Inc": 29.889999999999997,
      "Azi": 224.285687167886,
      "Tvd": 1908.713772275096,
      "Ns": -489.888867905943,
      "Ew": -470.446125043425
    },
    {
      "Md": 2116.569999999999,
      "Inc": 31.74999999999999,
      "Azi": 224.805687167886,
      "Tvd": 1990.2945420497722,
      "Ns": -524.5713410294891,
      "Ew": -504.59133343575206
    },
    {
      "Md": 2211.569999999999,
      "Inc": 33.32,
      "Azi": 225.615687167886,
      "Tvd": 2070.3834137605613,
      "Ns": -560.5586721110291,
      "Ew": -540.855316805882
    },
    {
      "Md": 2305.569999999999,
      "Inc": 34.25,
      "Azi": 224.535687167886,
      "Tvd": 2148.509498702048,
      "Ns": -597.473754984921,
      "Ew": -577.8595953410451
    },
    {
      "Md": 2400.569999999999,
      "Inc": 35.40999999999999,
      "Azi": 224.095687167886,
      "Tvd": 2226.489067678468,
      "Ns": -636.297113792627,
      "Ew": -615.76224563429
    },
    {
      "Md": 2495.569999999999,
      "Inc": 37.269999999999996,
      "Azi": 224.105687167886,
      "Tvd": 2303.0096119381865,
      "Ns": -676.721490193156,
      "Ew": -654.9372827405671
    },
    {
      "Md": 2590.569999999999,
      "Inc": 37.65999999999999,
      "Azi": 224.775687167886,
      "Tvd": 2378.4136653108762,
      "Ns": -717.977829097223,
      "Ew": -695.398008627209
    },
    {
      "Md": 2684.569999999999,
      "Inc": 38.1,
      "Azi": 224.335687167886,
      "Tvd": 2452.6076759591224,
      "Ns": -759.105545178286,
      "Ew": -735.8912174248801
    },
    {
      "Md": 2779.569999999999,
      "Inc": 38.28,
      "Azi": 223.49568716788602,
      "Tvd": 2527.274813794779,
      "Ns": -801.416246501893,
      "Ew": -776.628839675561
    },
    {
      "Md": 2874.569999999999,
      "Inc": 38.129999999999995,
      "Azi": 224.135687167886,
      "Tvd": 2601.9263671474473,
      "Ns": -843.812231328509,
      "Ew": -817.3066592319
    },
    {
      "Md": 2969.569999999999,
      "Inc": 37.53999999999999,
      "Azi": 224.115687167886,
      "Tvd": 2676.9551797683102,
      "Ns": -885.6404797217131,
      "Ew": -857.8775247632251
    },
    {
      "Md": 3064.569999999999,
      "Inc": 37.82999999999999,
      "Azi": 223.815687167886,
      "Tvd": 2752.1366060154014,
      "Ns": -927.4407641376,
      "Ew": -898.1945484348911
    },
    {
      "Md": 3159.569999999999,
      "Inc": 38.14,
      "Azi": 224.315687167886,
      "Tvd": 2827.013025782265,
      "Ns": -969.4517395406481,
      "Ew": -938.8584882106011
    },
    {
      "Md": 3255.569999999999,
      "Inc": 37.78,
      "Azi": 224.265687167886,
      "Tvd": 2902.703179030028,
      "Ns": -1011.720435909791,
      "Ew": -980.0935154073051
    },
    {
      "Md": 3350.569999999999,
      "Inc": 38.269999999999996,
      "Azi": 224.035687167886,
      "Tvd": 2977.538483438166,
      "Ns": -1053.709757066153,
      "Ew": -1020.855194937652
    },
    {
      "Md": 3445.569999999999,
      "Inc": 37.46,
      "Azi": 223.705687167886,
      "Tvd": 3052.5365593855263,
      "Ns": -1095.745164189344,
      "Ew": -1061.267488162973
    },
    {
      "Md": 3540.569999999999,
      "Inc": 36.989999999999995,
      "Azi": 222.845687167886,
      "Tvd": 3128.182140445573,
      "Ns": -1137.58432879268,
      "Ew": -1100.6644139134992
    },
    {
      "Md": 3635.569999999999,
      "Inc": 36.78999999999999,
      "Azi": 224.005687167886,
      "Tvd": 3204.163033787313,
      "Ns": -1179.00017530115,
      "Ew": -1139.8627718182022
    },
    {
      "Md": 3730.569999999999,
      "Inc": 37.15999999999999,
      "Azi": 225.035687167886,
      "Tvd": 3280.058953714182,
      "Ns": -1219.737491906172,
      "Ew": -1179.9272334859202
    },
    {
      "Md": 3825.569999999999,
      "Inc": 36.879999999999995,
      "Azi": 225.025687167886,
      "Tvd": 3355.909290197197,
      "Ns": -1260.1615072543582,
      "Ew": -1220.3945964960521
    },
    {
      "Md": 3920.569999999999,
      "Inc": 37.199999999999996,
      "Azi": 223.705687167886,
      "Tvd": 3431.7408497099273,
      "Ns": -1301.071043800352,
      "Ew": -1260.404796522368
    },
    {
      "Md": 4016.5699999999993,
      "Inc": 36.93,
      "Azi": 223.005687167886,
      "Tvd": 3508.3445418079,
      "Ns": -1343.1408579344402,
      "Ew": -1300.1281699787871
    },
    {
      "Md": 4111.57,
      "Inc": 36.769999999999996,
      "Azi": 223.375687167886,
      "Tvd": 3584.3644024686764,
      "Ns": -1384.679222488639,
      "Ew": -1339.122117074041
    },
    {
      "Md": 4206.57,
      "Inc": 37.699999999999996,
      "Azi": 224.15568716788601,
      "Tvd": 3659.999241685437,
      "Ns": -1426.1880059414161,
      "Ew": -1378.885703738496
    },
    {
      "Md": 4301.57,
      "Inc": 38.019999999999996,
      "Azi": 224.24568716788602,
      "Tvd": 3735.002860737264,
      "Ns": -1467.986630473309,
      "Ew": -1419.5342948311982
    },
    {
      "Md": 4397.57,
      "Inc": 37.78999999999999,
      "Azi": 224.345687167886,
      "Tvd": 3810.7497427680014,
      "Ns": -1510.199901826528,
      "Ew": -1460.7221125150452
    },
    {
      "Md": 4492.57,
      "Inc": 36.629999999999995,
      "Azi": 223.985687167886,
      "Tvd": 3886.4088580205603,
      "Ns": -1551.4079483653131,
      "Ew": -1500.750553084048
    },
    {
      "Md": 4587.57,
      "Inc": 36.89,
      "Azi": 223.21568716788602,
      "Tvd": 3962.518393431102,
      "Ns": -1592.579690453027,
      "Ew": -1539.9572124378271
    },
    {
      "Md": 4683.57,
      "Inc": 37.019999999999996,
      "Azi": 222.725687167886,
      "Tvd": 4039.232907062638,
      "Ns": -1634.8091276164482,
      "Ew": -1579.2959183152
    },
    {
      "Md": 4778.57,
      "Inc": 36.46999999999999,
      "Azi": 223.165687167886,
      "Tvd": 4115.356820894993,
      "Ns": -1676.4123126648733,
      "Ew": -1618.015933311794
    },
    {
      "Md": 4873.57,
      "Inc": 36.269999999999996,
      "Azi": 223.68568716788602,
      "Tvd": 4191.851384732422,
      "Ns": -1717.326430576171,
      "Ew": -1656.740417962658
    },
    {
      "Md": 4969.57,
      "Inc": 35.40999999999999,
      "Azi": 224.255687167886,
      "Tvd": 4269.6737776245345,
      "Ns": -1757.7819455338672,
      "Ew": -1695.7638390557102
    },
    {
      "Md": 5064.57,
      "Inc": 33.699999999999996,
      "Azi": 223.575687167886,
      "Tvd": 4347.911468486576,
      "Ns": -1796.5909074274252,
      "Ew": -1733.1406267856
    },
    {
      "Md": 5160.57,
      "Inc": 33.89999999999999,
      "Azi": 223.71568716788602,
      "Tvd": 4427.685949318671,
      "Ns": -1835.235316936779,
      "Ew": -1770.0002394369783
    },
    {
      "Md": 5255.57,
      "Inc": 33.269999999999996,
      "Azi": 224.055687167886,
      "Tvd": 4506.826900221216,
      "Ns": -1873.111017158339,
      "Ew": -1806.4288297356902
    },
    {
      "Md": 5350.57,
      "Inc": 32.14999999999999,
      "Azi": 224.095687167886,
      "Tvd": 4586.760194053483,
      "Ns": -1909.992067950015,
      "Ew": -1842.13834031958
    },
    {
      "Md": 5445.57,
      "Inc": 31.599999999999998,
      "Azi": 224.795687167886,
      "Tvd": 4667.434371359359,
      "Ns": -1945.807598150845,
      "Ew": -1877.2641756761661
    },
    {
      "Md": 5540.57,
      "Inc": 30.649999999999988,
      "Azi": 224.71568716788602,
      "Tvd": 4748.757397512488,
      "Ns": -1980.6779018582272,
      "Ew": -1911.839024717228
    },
    {
      "Md": 5635.57,
      "Inc": 30.25,
      "Azi": 224.695687167886,
      "Tvd": 4830.654047003824,
      "Ns": -2014.895658690805,
      "Ew": -1945.707110584829
    },
    {
      "Md": 5730.57,
      "Inc": 30.219999999999988,
      "Azi": 225.085687167886,
      "Tvd": 4912.7310259349,
      "Ns": -2048.7859172223143,
      "Ew": -1979.46819564669
    },
    {
      "Md": 5825.57,
      "Inc": 29.58,
      "Azi": 224.40568716788601,
      "Tvd": 4995.086029121862,
      "Ns": -2082.4176130704764,
      "Ew": -2012.8064968322042
    },
    {
      "Md": 5843.57,
      "Inc": 29.489999999999988,
      "Azi": 224.415687167886,
      "Tvd": 5010.747012645852,
      "Ns": -2088.756108652199,
      "Ew": -2019.015925308488
    },
    {
      "Md": 5930.57,
      "Inc": 29.809999999999988,
      "Azi": 224.15568716788601,
      "Tvd": 5086.355475230073,
      "Ns": -2119.56650109163,
      "Ew": -2049.066836275832
    },
    {
      "Md": 6025.57,
      "Inc": 28.349999999999998,
      "Azi": 224.99568716788602,
      "Tvd": 5169.378063735173,
      "Ns": -2152.4603586308663,
      "Ew": -2081.466179451741
    },
    {
      "Md": 6120.57,
      "Inc": 26.439999999999998,
      "Azi": 224.615687167886,
      "Tvd": 5253.7205001495095,
      "Ns": -2183.4689189878095,
      "Ew": -2112.271696305091
    },
    {
      "Md": 6214.57,
      "Inc": 24.91,
      "Azi": 224.545687167886,
      "Tvd": 5338.437003580204,
      "Ns": -2212.475884038054,
      "Ew": -2140.8581400786547
    },
    {
      "Md": 6309.57,
      "Inc": 23.369999999999997,
      "Azi": 224.625687167886,
      "Tvd": 5425.126540617653,
      "Ns": -2240.146013022714,
      "Ew": -2168.129820815911
    },
    {
      "Md": 6404.57,
      "Inc": 23.599999999999998,
      "Azi": 224.725687167886,
      "Tvd": 5512.257106974018,
      "Ns": -2267.066872690009,
      "Ew": -2194.747845500548
    },
    {
      "Md": 6468.57,
      "Inc": 23.82,
      "Azi": 224.775687167886,
      "Tvd": 5570.854986859337,
      "Ns": -2285.343147286676,
      "Ew": -2212.865825115954
    }
  ],
  "PorePressureGradient": [
    {
      "formationname": "K1 INFERIOR",
      "value": 2192.33,
      "depth_tvd": 5241.59
    }
  ],
  "FracturePressureGradient": [
    {
      "formationname": "K1 INFERIOR",
      "value": 0.49400000000000005,
      "depth_tvd": 5241.7699999999995
    }
  ],
  "TemperatureGradient": [
    {
      "formationname": "K1 INFERIOR",
      "value": 191,
      "depth_tvd": 5241.7300000000005
    }
  ],
  "ReferenceDepths": {
    "Offshore": false,
    "AirGap": 32.5,
    "WaterDepth": 1330.9,
    "Mudline": 32.5,
    "DatumElevation": 1363.4,
    "SystemDatum": "Mean Sea Level"
  },
  "Perforations": [
    {
      "ref_id": "CdWellboreOpeningT/r2edFaIgZ1+s2bHGqmJCc",
      "StartMD": 6185.57,
      "EndMD": 6190.57,
      "Key": "00003",
      "Status": "OPEN",
      "name": ""
    },
    {
      "ref_id": "CdWellboreOpeningT/r2edFaIgZ1+s2bHGqmJCc",
      "StartMD": 6176.57,
      "EndMD": 6182.57,
      "Key": "00003",
      "Status": "OPEN",
      "name": ""
    },
    {
      "ref_id": "CdWellboreOpeningT/r2edFaIgZ1+s2bHGqmJCc",
      "StartMD": 6136.57,
      "EndMD": 6145.57,
      "Key": "00003",
      "Status": "OPEN",
      "name": ""
    },
    {
      "ref_id": "CdWellboreOpeningT/r2edFaIgZ1+s2bHGqmJCc",
      "StartMD": 6154.57,
      "EndMD": 6159.57,
      "Key": "00003",
      "Status": "OPEN",
      "name": ""
    },
    {
      "ref_id": "CdWellboreOpeningT/r2edFaIgZ1+s2bHGqmJCc",
      "StartMD": 6100.57,
      "EndMD": 6119.57,
      "Key": "00003",
      "Status": "OPEN",
      "name": ""
    }
  ]
}